pyiron_database/__init__.py
pyiron_database/_version.py
pyiron_database/generic_storage/__init__.py
pyiron_database/generic_storage/dataclass_helpers.py
pyiron_database/generic_storage/hdf5_storage.py
pyiron_database/generic_storage/interface.py
pyiron_database/generic_storage/json_storage.py
pyiron_database/generic_storage/pickle_storage.py
pyiron_database/instance_database/InstanceDatabase.py
pyiron_database/instance_database/Neo4jInstanceDatabase.py
pyiron_database/instance_database/PostgreSQLInstanceDatabase.py
pyiron_database/instance_database/__init__.py
pyiron_database/instance_database/node.py
pyiron_database/obj_reconstruction/__init__.py
pyiron_database/obj_reconstruction/util.py
pyiron_database-0.0.8.dist-info/LICENSE
pyiron_database-0.0.8.dist-info/METADATA
pyiron_database-0.0.8.dist-info/WHEEL
pyiron_database-0.0.8.dist-info/top_level.txt
pyiron_database-0.0.8.dist-info/RECORD
