Metadata-Version: 2.2
Name: pyiron_database
Version: 0.0.8
Summary: pyiron_database - Database support for pyiron_workflow.
Author-email: Sebastian Eibl <sebastian.eibl@mpcdf.mpg.de>
License: BSD 3-Clause License
Project-URL: Homepage, https://pyiron.org/
Project-URL: Documentation, https://pyiron_database.readthedocs.io
Project-URL: Repository, https://github.com/pyiron/pyiron_database
Keywords: pyiron_workflow
Classifier: Development Status :: 3 - Alpha
Classifier: Topic :: Scientific/Engineering
Classifier: License :: OSI Approved :: BSD License
Classifier: Intended Audience :: Science/Research
Classifier: Operating System :: OS Independent
Classifier: Programming Language :: Python :: 3.10
Classifier: Programming Language :: Python :: 3.11
Classifier: Programming Language :: Python :: 3.12
Requires-Python: <3.13,>=3.10
License-File: LICENSE
Requires-Dist: h5py==3.12.1
Requires-Dist: pyiron_workflow==0.12.0
Requires-Dist: setuptools==75.8.0
Requires-Dist: versioneer[toml]==0.29
Provides-Extra: neo4j
Requires-Dist: neo4j-python-driver-rust-ext==5.25.0.0; extra == "neo4j"
Provides-Extra: postgresql
Requires-Dist: psycopg2==2.9.9; extra == "postgresql"
Requires-Dist: sqlalchemy==2.0.38; extra == "postgresql"
